{
  "institution": "KEK",
  "component": "20UPGB42304006",
  "componentType": "BARE_MODULE",
  "stage": "BAREMODULERECEPTION",
  "testType": "QUAD_BARE_MODULE_METROLOGY",
  "date": "2023-09-10T14:45:01.642+09:00",
  "results": {
    "SENSOR_X": 39.501,
    "SENSOR_Y": 41.095,
    "FECHIPS_X": 42.21,
    "FECHIPS_Y": 40.286,
    "FECHIP_THICKNESS": 156.4,
    "FECHIP_THICKNESS_STD_DEVIATION": 1.9,
    "BAREMODULE_THICKNESS": 319.4,
    "BAREMODULE_THICKNESS_STD_DEVIATION": 2.4,
    "SENSOR_THICKNESS": 157.0,
    "SENSOR_THICKNESS_STD_DEVIATION": 2.4
  },
  "passed": true,
  "problems": false,
  "runNumber": "1"
}