{
  "component": "20UPGM22601036",
  "componentType": "MODULE",
  "stage": "MODULE/ASSEMBLY",
  "testType": "QUAD_MODULE_METROLOGY",
  "date": "2023-07-21T14:00:04.317624",
  "results": {
    "PCB_BAREMODULE_POSITION_TOP_RIGHT": [
      2.192499999999999,
      0.7517999999999994
    ],
    "PCB_BAREMODULE_POSITION_BOTTOM_LEFT": [
      2.1863500000000045,
      0.844850000000001
    ],
    "ANGLE_PCB_BM": 0.0,
    "AVERAGE_THICKNESS": [
      0.621068270328931,
      0.5736928836270492,
      0.5522367058679594,
      0.5949319338711279
    ],
    "STD_DEVIATION_THICKNESS": [
      0.002,
      0.002,
      0.002,
      0.002
    ],
    "THICKNESS_VARIATION_PICKUP_AREA": 0.0688315644609716,
    "THICKNESS_INCLUDING_POWER_CONNECTOR": 1.882366925494322,
    "HV_CAPACITOR_THICKNESS": 2.2411581921211856
  },
  "passed": true,
  "problems": false,
  "runNumber": 1
}