{
  "institution": "HR",
  "component": "20UPGM22601049",
  "componentType": "MODULE",
  "stage": "MODULE/ASSEMBLY",
  "testType": "QUAD_MODULE_METROLOGY",
  "date": "2023-08-07T12:13:09.139Z",
  "results": {
    "PCB_BAREMODULE_POSITION_TOP_RIGHT": [
      0.0,
      0.0
    ],
    "PCB_BAREMODULE_POSITION_BOTTOM_LEFT": [
      0.0,
      0.0
    ],
    "ANGLE_PCB_BM": 0.0,
    "AVERAGE_THICKNESS": [
      0.5983352343963615,
      0.6150934318096821,
      0.704526072360216,
      0.8495084521370222
    ],
    "STD_DEVIATION_THICKNESS": [
      0.002,
      0.002,
      0.002,
      0.002
    ],
    "THICKNESS_VARIATION_PICKUP_AREA": 0.251,
    "THICKNESS_INCLUDING_POWER_CONNECTOR": 1.954,
    "HV_CAPACITOR_THICKNESS": 2.344
  },
  "passed": true,
  "problems": false,
  "runNumber": "1"
}